<stg><name>dense_latency<ap_fixed<8, 4, 5, 3, 0>, ap_fixed<8, 4, 5, 3, 0>, config8></name>


<trans_list>

<trans id="44" from="1" to="2">
<condition id="-1">
<or_exp><and_exp></and_exp></or_exp>
</condition>
</trans>

<trans id="45" from="2" to="3">
<condition id="-1">
<or_exp><and_exp></and_exp></or_exp>
</condition>
</trans>

<trans id="46" from="3" to="4">
<condition id="-1">
<or_exp><and_exp></and_exp></or_exp>
</condition>
</trans>

<trans id="47" from="4" to="5">
<condition id="-1">
<or_exp><and_exp></and_exp></or_exp>
</condition>
</trans>
</trans_list>



<state_list>

<state id="1" st_id="1">

<operation id="6" st_id="1" stage="1" lat="1">
<core>NULL</core>
<MemPortIdVec></MemPortIdVec>
<condition id="-1">
<or_exp><and_exp></and_exp></or_exp>
</condition>

<Node id="7" bw="8" op_0_bw="8" op_1_bw="8">
<![CDATA[
entry:2 %p_read_3 = read i8 @_ssdm_op_Read.ap_auto.i8, i8 %p_read3

]]></Node>
<StgValue><ssdm name="p_read_3"/></StgValue>
</operation>

<operation id="7" st_id="1" stage="1" lat="1">
<core>NULL</core>
<MemPortIdVec></MemPortIdVec>
<condition id="-1">
<or_exp><and_exp></and_exp></or_exp>
</condition>

<Node id="8" bw="8" op_0_bw="8" op_1_bw="8">
<![CDATA[
entry:3 %p_read_4 = read i8 @_ssdm_op_Read.ap_auto.i8, i8 %p_read2

]]></Node>
<StgValue><ssdm name="p_read_4"/></StgValue>
</operation>

<operation id="8" st_id="1" stage="1" lat="1">
<core>NULL</core>
<MemPortIdVec></MemPortIdVec>
<condition id="-1">
<or_exp><and_exp></and_exp></or_exp>
</condition>

<Node id="9" bw="8" op_0_bw="8" op_1_bw="8">
<![CDATA[
entry:4 %p_read_5 = read i8 @_ssdm_op_Read.ap_auto.i8, i8 %p_read1

]]></Node>
<StgValue><ssdm name="p_read_5"/></StgValue>
</operation>

<operation id="9" st_id="1" stage="1" lat="1">
<core>NULL</core>
<MemPortIdVec></MemPortIdVec>
<condition id="-1">
<or_exp><and_exp></and_exp></or_exp>
</condition>

<Node id="10" bw="8" op_0_bw="8" op_1_bw="8">
<![CDATA[
entry:5 %p_read_6 = read i8 @_ssdm_op_Read.ap_auto.i8, i8 %p_read

]]></Node>
<StgValue><ssdm name="p_read_6"/></StgValue>
</operation>

<operation id="10" st_id="1" stage="1" lat="1">
<core>NULL</core>
<MemPortIdVec></MemPortIdVec>
<condition id="-1">
<or_exp><and_exp></and_exp></or_exp>
</condition>

<Node id="11" bw="7" op_0_bw="8">
<![CDATA[
entry:6 %trunc_ln1273 = trunc i8 %p_read_6

]]></Node>
<StgValue><ssdm name="trunc_ln1273"/></StgValue>
</operation>

<operation id="11" st_id="1" stage="1" lat="1">
<core>NULL</core>
<MemPortIdVec></MemPortIdVec>
<condition id="-1">
<or_exp><and_exp></and_exp></or_exp>
</condition>

<Node id="12" bw="11" op_0_bw="11" op_1_bw="7" op_2_bw="4">
<![CDATA[
entry:7 %shl_ln = bitconcatenate i11 @_ssdm_op_BitConcatenate.i11.i7.i4, i7 %trunc_ln1273, i4 0

]]></Node>
<StgValue><ssdm name="shl_ln"/></StgValue>
</operation>

<operation id="12" st_id="1" stage="1" lat="1">
<core>NULL</core>
<MemPortIdVec></MemPortIdVec>
<condition id="-1">
<or_exp><and_exp></and_exp></or_exp>
</condition>

<Node id="13" bw="10" op_0_bw="10" op_1_bw="8" op_2_bw="2">
<![CDATA[
entry:8 %shl_ln1273_1 = bitconcatenate i10 @_ssdm_op_BitConcatenate.i10.i8.i2, i8 %p_read_6, i2 0

]]></Node>
<StgValue><ssdm name="shl_ln1273_1"/></StgValue>
</operation>

<operation id="13" st_id="1" stage="1" lat="1">
<core>NULL</core>
<MemPortIdVec></MemPortIdVec>
<condition id="-1">
<or_exp><and_exp></and_exp></or_exp>
</condition>

<Node id="14" bw="11" op_0_bw="10">
<![CDATA[
entry:9 %sext_ln1273 = sext i10 %shl_ln1273_1

]]></Node>
<StgValue><ssdm name="sext_ln1273"/></StgValue>
</operation>

<operation id="14" st_id="1" stage="1" lat="1">
<core>Adder</core>
<MemPortIdVec></MemPortIdVec>
<condition id="-1">
<or_exp><and_exp></and_exp></or_exp>
</condition>

<Node id="15" bw="11" op_0_bw="11" op_1_bw="11">
<![CDATA[
entry:10 %r_V = sub i11 %sext_ln1273, i11 %shl_ln

]]></Node>
<StgValue><ssdm name="r_V"/></StgValue>
</operation>

<operation id="15" st_id="1" stage="1" lat="1">
<core>NULL</core>
<MemPortIdVec></MemPortIdVec>
<condition id="-1">
<or_exp><and_exp></and_exp></or_exp>
</condition>

<Node id="16" bw="8" op_0_bw="8" op_1_bw="11" op_2_bw="32" op_3_bw="32">
<![CDATA[
entry:11 %trunc_ln = partselect i8 @_ssdm_op_PartSelect.i8.i11.i32.i32, i11 %r_V, i32 3, i32 10

]]></Node>
<StgValue><ssdm name="trunc_ln"/></StgValue>
</operation>

<operation id="16" st_id="1" stage="1" lat="1">
<core>NULL</core>
<MemPortIdVec></MemPortIdVec>
<condition id="-1">
<or_exp><and_exp></and_exp></or_exp>
</condition>

<Node id="22" bw="11" op_0_bw="8">
<![CDATA[
entry:17 %sext_ln70 = sext i8 %p_read_4

]]></Node>
<StgValue><ssdm name="sext_ln70"/></StgValue>
</operation>

<operation id="17" st_id="1" stage="1" lat="1">
<core>NULL</core>
<MemPortIdVec></MemPortIdVec>
<condition id="-1">
<or_exp><and_exp></and_exp></or_exp>
</condition>

<Node id="23" bw="11" op_0_bw="11" op_1_bw="8" op_2_bw="3">
<![CDATA[
entry:18 %shl_ln1273_4 = bitconcatenate i11 @_ssdm_op_BitConcatenate.i11.i8.i3, i8 %p_read_4, i3 0

]]></Node>
<StgValue><ssdm name="shl_ln1273_4"/></StgValue>
</operation>

<operation id="18" st_id="1" stage="1" lat="1">
<core>Adder</core>
<MemPortIdVec></MemPortIdVec>
<condition id="-1">
<or_exp><and_exp></and_exp></or_exp>
</condition>

<Node id="24" bw="11" op_0_bw="11" op_1_bw="11">
<![CDATA[
entry:19 %r_V_2 = add i11 %shl_ln1273_4, i11 %sext_ln70

]]></Node>
<StgValue><ssdm name="r_V_2"/></StgValue>
</operation>

<operation id="19" st_id="1" stage="1" lat="1">
<core>NULL</core>
<MemPortIdVec></MemPortIdVec>
<condition id="-1">
<or_exp><and_exp></and_exp></or_exp>
</condition>

<Node id="25" bw="8" op_0_bw="8" op_1_bw="11" op_2_bw="32" op_3_bw="32">
<![CDATA[
entry:20 %trunc_ln818_3 = partselect i8 @_ssdm_op_PartSelect.i8.i11.i32.i32, i11 %r_V_2, i32 3, i32 10

]]></Node>
<StgValue><ssdm name="trunc_ln818_3"/></StgValue>
</operation>

<operation id="20" st_id="1" stage="1" lat="1">
<core>NULL</core>
<MemPortIdVec></MemPortIdVec>
<condition id="-1">
<or_exp><and_exp></and_exp></or_exp>
</condition>

<Node id="26" bw="11" op_0_bw="8">
<![CDATA[
entry:21 %sext_ln1270 = sext i8 %p_read_3

]]></Node>
<StgValue><ssdm name="sext_ln1270"/></StgValue>
</operation>

<operation id="21" st_id="1" stage="3" lat="3">
<core>Mul_DSP</core>
<MemPortIdVec></MemPortIdVec>
<condition id="-1">
<or_exp><and_exp></and_exp></or_exp>
</condition>

<Node id="27" bw="11" op_0_bw="11" op_1_bw="11">
<![CDATA[
entry:22 %mul_ln1270 = mul i11 %sext_ln1270, i11 11

]]></Node>
<StgValue><ssdm name="mul_ln1270"/></StgValue>
</operation>

<operation id="22" st_id="1" stage="1" lat="1">
<core>Adder</core>
<MemPortIdVec></MemPortIdVec>
<condition id="-1">
<or_exp><and_exp></and_exp></or_exp>
</condition>

<Node id="29" bw="8" op_0_bw="8" op_1_bw="8">
<![CDATA[
entry:24 %add_ln813 = add i8 %trunc_ln818_3, i8 248

]]></Node>
<StgValue><ssdm name="add_ln813"/></StgValue>
</operation>
</state>

<state id="2" st_id="2">

<operation id="23" st_id="2" stage="1" lat="1">
<core>NULL</core>
<MemPortIdVec></MemPortIdVec>
<condition id="-1">
<or_exp><and_exp></and_exp></or_exp>
</condition>

<Node id="17" bw="11" op_0_bw="11" op_1_bw="8" op_2_bw="3">
<![CDATA[
entry:12 %shl_ln1273_2 = bitconcatenate i11 @_ssdm_op_BitConcatenate.i11.i8.i3, i8 %p_read_5, i3 0

]]></Node>
<StgValue><ssdm name="shl_ln1273_2"/></StgValue>
</operation>

<operation id="24" st_id="2" stage="1" lat="1">
<core>NULL</core>
<MemPortIdVec></MemPortIdVec>
<condition id="-1">
<or_exp><and_exp></and_exp></or_exp>
</condition>

<Node id="18" bw="9" op_0_bw="9" op_1_bw="8" op_2_bw="1">
<![CDATA[
entry:13 %shl_ln1273_3 = bitconcatenate i9 @_ssdm_op_BitConcatenate.i9.i8.i1, i8 %p_read_5, i1 0

]]></Node>
<StgValue><ssdm name="shl_ln1273_3"/></StgValue>
</operation>

<operation id="25" st_id="2" stage="1" lat="1">
<core>NULL</core>
<MemPortIdVec></MemPortIdVec>
<condition id="-1">
<or_exp><and_exp></and_exp></or_exp>
</condition>

<Node id="19" bw="11" op_0_bw="9">
<![CDATA[
entry:14 %sext_ln1273_1 = sext i9 %shl_ln1273_3

]]></Node>
<StgValue><ssdm name="sext_ln1273_1"/></StgValue>
</operation>

<operation id="26" st_id="2" stage="1" lat="1">
<core>Adder</core>
<MemPortIdVec></MemPortIdVec>
<condition id="-1">
<or_exp><and_exp></and_exp></or_exp>
</condition>

<Node id="20" bw="11" op_0_bw="11" op_1_bw="11">
<![CDATA[
entry:15 %r_V_1 = add i11 %shl_ln1273_2, i11 %sext_ln1273_1

]]></Node>
<StgValue><ssdm name="r_V_1"/></StgValue>
</operation>

<operation id="27" st_id="2" stage="1" lat="1">
<core>NULL</core>
<MemPortIdVec></MemPortIdVec>
<condition id="-1">
<or_exp><and_exp></and_exp></or_exp>
</condition>

<Node id="21" bw="8" op_0_bw="8" op_1_bw="11" op_2_bw="32" op_3_bw="32">
<![CDATA[
entry:16 %trunc_ln818_2 = partselect i8 @_ssdm_op_PartSelect.i8.i11.i32.i32, i11 %r_V_1, i32 3, i32 10

]]></Node>
<StgValue><ssdm name="trunc_ln818_2"/></StgValue>
</operation>

<operation id="28" st_id="2" stage="2" lat="3">
<core>Mul_DSP</core>
<MemPortIdVec></MemPortIdVec>
<condition id="-1">
<or_exp><and_exp></and_exp></or_exp>
</condition>

<Node id="27" bw="11" op_0_bw="11" op_1_bw="11">
<![CDATA[
entry:22 %mul_ln1270 = mul i11 %sext_ln1270, i11 11

]]></Node>
<StgValue><ssdm name="mul_ln1270"/></StgValue>
</operation>

<operation id="29" st_id="2" stage="1" lat="1">
<core>Adder</core>
<MemPortIdVec></MemPortIdVec>
<condition id="-1">
<or_exp><and_exp></and_exp></or_exp>
</condition>

<Node id="30" bw="8" op_0_bw="8" op_1_bw="8">
<![CDATA[
entry:25 %add_ln813_1 = add i8 %add_ln813, i8 %trunc_ln818_2

]]></Node>
<StgValue><ssdm name="add_ln813_1"/></StgValue>
</operation>
</state>

<state id="3" st_id="3">

<operation id="30" st_id="3" stage="1" lat="3">
<core>Mul_DSP</core>
<MemPortIdVec></MemPortIdVec>
<condition id="-1">
<or_exp><and_exp></and_exp></or_exp>
</condition>

<Node id="27" bw="11" op_0_bw="11" op_1_bw="11">
<![CDATA[
entry:22 %mul_ln1270 = mul i11 %sext_ln1270, i11 11

]]></Node>
<StgValue><ssdm name="mul_ln1270"/></StgValue>
</operation>

<operation id="31" st_id="3" stage="1" lat="1">
<core>NULL</core>
<MemPortIdVec></MemPortIdVec>
<condition id="-1">
<or_exp><and_exp></and_exp></or_exp>
</condition>

<Node id="28" bw="8" op_0_bw="8" op_1_bw="11" op_2_bw="32" op_3_bw="32">
<![CDATA[
entry:23 %trunc_ln818_4 = partselect i8 @_ssdm_op_PartSelect.i8.i11.i32.i32, i11 %mul_ln1270, i32 3, i32 10

]]></Node>
<StgValue><ssdm name="trunc_ln818_4"/></StgValue>
</operation>
</state>

<state id="4" st_id="4">

<operation id="32" st_id="4" stage="1" lat="1">
<core>Adder</core>
<MemPortIdVec></MemPortIdVec>
<condition id="-1">
<or_exp><and_exp></and_exp></or_exp>
</condition>

<Node id="31" bw="8" op_0_bw="8" op_1_bw="8">
<![CDATA[
entry:26 %add_ln813_2 = add i8 %trunc_ln818_4, i8 248

]]></Node>
<StgValue><ssdm name="add_ln813_2"/></StgValue>
</operation>
</state>

<state id="5" st_id="5">

<operation id="33" st_id="5" stage="1" lat="1">
<core>NULL</core>
<MemPortIdVec></MemPortIdVec>
<condition id="-1">
<or_exp><and_exp></and_exp></or_exp>
</condition>

<Node id="5" bw="0" op_0_bw="0" op_1_bw="32" op_2_bw="32" op_3_bw="32" op_4_bw="32" op_5_bw="0">
<![CDATA[
entry:0 %specpipeline_ln33 = specpipeline void @_ssdm_op_SpecPipeline, i32 1, i32 0, i32 0, i32 0, void @empty_0

]]></Node>
<StgValue><ssdm name="specpipeline_ln33"/></StgValue>
</operation>

<operation id="34" st_id="5" stage="1" lat="1">
<core>NULL</core>
<MemPortIdVec></MemPortIdVec>
<condition id="-1">
<or_exp><and_exp></and_exp></or_exp>
</condition>

<Node id="6" bw="0" op_0_bw="0" op_1_bw="64" op_2_bw="0" op_3_bw="0" op_4_bw="0" op_5_bw="0">
<![CDATA[
entry:1 %specresourcelimit_ln33 = specresourcelimit void @_ssdm_op_SpecResourceLimit, i64 4, void @empty_1, void @empty_0, void @empty_0, void @empty_0

]]></Node>
<StgValue><ssdm name="specresourcelimit_ln33"/></StgValue>
</operation>

<operation id="35" st_id="5" stage="1" lat="1">
<core>Adder</core>
<MemPortIdVec></MemPortIdVec>
<condition id="-1">
<or_exp><and_exp></and_exp></or_exp>
</condition>

<Node id="32" bw="8" op_0_bw="8" op_1_bw="8">
<![CDATA[
entry:27 %add_ln813_3 = add i8 %add_ln813_2, i8 %trunc_ln

]]></Node>
<StgValue><ssdm name="add_ln813_3"/></StgValue>
</operation>

<operation id="36" st_id="5" stage="1" lat="1">
<core>NULL</core>
<MemPortIdVec></MemPortIdVec>
<condition id="-1">
<or_exp><and_exp></and_exp></or_exp>
</condition>

<Node id="33" bw="16" op_0_bw="16" op_1_bw="8">
<![CDATA[
entry:28 %mrv = insertvalue i16 <undef>, i8 %add_ln813_3

]]></Node>
<StgValue><ssdm name="mrv"/></StgValue>
</operation>

<operation id="37" st_id="5" stage="1" lat="1">
<core>NULL</core>
<MemPortIdVec></MemPortIdVec>
<condition id="-1">
<or_exp><and_exp></and_exp></or_exp>
</condition>

<Node id="34" bw="16" op_0_bw="16" op_1_bw="8">
<![CDATA[
entry:29 %mrv_1 = insertvalue i16 %mrv, i8 %add_ln813_1

]]></Node>
<StgValue><ssdm name="mrv_1"/></StgValue>
</operation>

<operation id="38" st_id="5" stage="1" lat="1">
<core>NULL</core>
<MemPortIdVec></MemPortIdVec>
<condition id="-1">
<or_exp><and_exp></and_exp></or_exp>
</condition>

<Node id="35" bw="0" op_0_bw="16">
<![CDATA[
entry:30 %ret_ln68 = ret i16 %mrv_1

]]></Node>
<StgValue><ssdm name="ret_ln68"/></StgValue>
</operation>
</state>
</state_list>


<ports>
</ports>


<dataflows>
</dataflows>


</stg>
